pyproteininference/__init__.py
pyproteininference/datastore.py
pyproteininference/export.py
pyproteininference/heuristic.py
pyproteininference/in_silico_digest.py
pyproteininference/inference.py
pyproteininference/parameters.py
pyproteininference/physical.py
pyproteininference/pipeline.py
pyproteininference/reader.py
pyproteininference/scoring.py
pyproteininference/gui/__init__.py
pyproteininference/gui/configuration.py
pyproteininference/gui/gui.py
pyproteininference-1.1.1.data/scripts/protein_inference_cli.py
pyproteininference-1.1.1.data/scripts/protein_inference_gui.py
pyproteininference-1.1.1.data/scripts/protein_inference_heuristic_cli.py
pyproteininference-1.1.1.dist-info/LICENSE
pyproteininference-1.1.1.dist-info/METADATA
pyproteininference-1.1.1.dist-info/WHEEL
pyproteininference-1.1.1.dist-info/pbr.json
pyproteininference-1.1.1.dist-info/top_level.txt
pyproteininference-1.1.1.dist-info/RECORD
