Metadata-Version: 2.1
Name: pyproteininference
Version: 1.1.1
Summary: Python Package for running custom protein inference algorithms on tab-formatted tandem MS/MS search results.
Home-page: https://github.com/thinkle12/pyproteininference
Author: Trent Hinkle
Author-email: hinklet@gene.com
License: Apache-2
Keywords: proteininference
Platform: UNKNOWN
Classifier: Development Status :: 4 - Beta
Classifier: Intended Audience :: Developers
Classifier: Topic :: Scientific/Engineering :: Bio-Informatics
Classifier: License :: OSI Approved :: Apache Software License
Classifier: Programming Language :: Python :: 3
Classifier: Programming Language :: Python :: 3.9
Classifier: Programming Language :: Python :: 3.10
Classifier: Programming Language :: Python :: 3.11
License-File: LICENSE
Requires-Dist: numpy<2.0.0,>=1.19.2
Requires-Dist: pyteomics<5.0.0,>=4.7.5
Requires-Dist: pulp<3.0.0,>=2.8
Requires-Dist: PyYAML<6.0.2,>=6.0.0
Requires-Dist: matplotlib<4.0.0,>=3.3.4
Requires-Dist: lxml<6.0.0,>=5.3.0
Requires-Dist: nicegui<3.0.0,>=2.8.0
Requires-Dist: pyopenms<4.0.0,>=3.2.0
Requires-Dist: pywebview<6.0.0,>=5.3.0
Requires-Dist: tqdm<5.0.0,>=4.67.0
